odoo/addons/partner_parent_tag/README.rst
odoo/addons/partner_parent_tag/__init__.py
odoo/addons/partner_parent_tag/__manifest__.py
odoo/addons/partner_parent_tag/models/__init__.py
odoo/addons/partner_parent_tag/models/res_partner.py
odoo/addons/partner_parent_tag/readme/CONTRIBUTORS.md
odoo/addons/partner_parent_tag/readme/DESCRIPTION.md
odoo/addons/partner_parent_tag/static/description/icon.png
odoo/addons/partner_parent_tag/static/description/index.html
odoo/addons/partner_parent_tag/tests/__init__.py
odoo/addons/partner_parent_tag/tests/test_partner_parent_tag.py
odoo_addon_partner_parent_tag-17.0.1.0.0.1.dist-info/METADATA
odoo_addon_partner_parent_tag-17.0.1.0.0.1.dist-info/WHEEL
odoo_addon_partner_parent_tag-17.0.1.0.0.1.dist-info/top_level.txt
odoo_addon_partner_parent_tag-17.0.1.0.0.1.dist-info/RECORD
